setup.py
mofish_lzc.egg-info/PKG-INFO
mofish_lzc.egg-info/SOURCES.txt
mofish_lzc.egg-info/dependency_links.txt
mofish_lzc.egg-info/entry_points.txt
mofish_lzc.egg-info/requires.txt
mofish_lzc.egg-info/top_level.txt
src/__init__.py
src/main.py
src/utils.py